{
  "name": "7",
  "gridCols": 24,
  "gridRows": 16,
  "cellSize": 1.0,
  "startCell": {
    "col": 0,
    "row": 8
  },
  "endCell": {
    "col": 23,
    "row": 7
  },
  "pathWaypoints": [
    {
      "col": 3,
      "row": 8
    },
    {
      "col": 3,
      "row": 3
    },
    {
      "col": 8,
      "row": 3
    },
    {
      "col": 8,
      "row": 12
    },
    {
      "col": 13,
      "row": 12
    },
    {
      "col": 13,
      "row": 3
    },
    {
      "col": 18,
      "row": 3
    },
    {
      "col": 18,
      "row": 12
    }
  ],
  "waves": [
    {
      "delayBeforeWave": 3.0,
      "entries": [
        {
          "enemyType": "Basic",
          "count": 12,
          "spawnInterval": 1.0
        }
      ]
    },
    {
      "delayBeforeWave": 4.0,
      "entries": [
        {
          "enemyType": "Basic",
          "count": 8,
          "spawnInterval": 0.7
        },
        {
          "enemyType": "Fast",
          "count": 6,
          "spawnInterval": 1.0
        }
      ]
    },
    {
      "delayBeforeWave": 4.0,
      "entries": [
        {
          "enemyType": "Fast",
          "count": 10,
          "spawnInterval": 0.8
        },
        {
          "enemyType": "Tank",
          "count": 3,
          "spawnInterval": 2.2
        }
      ]
    },
    {
      "delayBeforeWave": 5.0,
      "entries": [
        {
          "enemyType": "Basic",
          "count": 15,
          "spawnInterval": 0.6
        }
      ]
    },
    {
      "delayBeforeWave": 5.0,
      "entries": [
        {
          "enemyType": "Basic",
          "count": 8,
          "spawnInterval": 0.5
        },
        {
          "enemyType": "Fast",
          "count": 8,
          "spawnInterval": 0.6
        },
        {
          "enemyType": "Tank",
          "count": 3,
          "spawnInterval": 2.0
        }
      ]
    },
    {
      "delayBeforeWave": 5.0,
      "entries": [
        {
          "enemyType": "Fast",
          "count": 12,
          "spawnInterval": 0.5
        },
        {
          "enemyType": "Tank",
          "count": 5,
          "spawnInterval": 1.5
        }
      ]
    }
  ]
}